gravity_dam/__init__.py
gravity_dam-0.0.0.dist-info/METADATA
gravity_dam-0.0.0.dist-info/WHEEL
gravity_dam-0.0.0.dist-info/RECORD
