Metadata-Version: 2.1
Name: gravity-dam
Version: 0.0.0
Summary: A Python library that combines various stream constraints and stream regularization algorithms. (It's like a gravity dam that uses itself to resist the pressure of the water)
License: "Apache Software License"
Author: so1n
Author-email: so1n897046026@gmail.com
Requires-Python: >=3.8,<4.0
Classifier: License :: Other/Proprietary License
Classifier: Programming Language :: Python :: 3
Classifier: Programming Language :: Python :: 3.8
Classifier: Programming Language :: Python :: 3.9
Classifier: Programming Language :: Python :: 3.10
Classifier: Programming Language :: Python :: 3.11
